queueless/__init__.py
queueless/client.py
queueless/log.py
queueless/records.py
queueless/sql.py
queueless/task.py
queueless/worker.py
queueless-0.1.0.dist-info/LICENSE
queueless-0.1.0.dist-info/WHEEL
queueless-0.1.0.dist-info/METADATA
queueless-0.1.0.dist-info/RECORD
